{
  "docusaurus-plugin-content-docs": {
    "default": {
      "path": "/github-pages-docusaurus/",
      "versions": [
        {
          "name": "current",
          "label": "Next",
          "isLast": true,
          "path": "/github-pages-docusaurus/",
          "mainDocId": "intro",
          "docs": [
            {
              "id": "intro",
              "path": "/github-pages-docusaurus/",
              "sidebar": "tutorialSidebar"
            }
          ],
          "draftIds": [],
          "sidebars": {
            "tutorialSidebar": {
              "link": {
                "path": "/github-pages-docusaurus/",
                "label": "intro"
              }
            }
          }
        }
      ],
      "breadcrumbs": true
    }
  }
}